spellcure/__init__.py
spellcure/corrector.py
spellcure-1.0.0.dist-info/METADATA
spellcure-1.0.0.dist-info/WHEEL
spellcure-1.0.0.dist-info/top_level.txt
spellcure-1.0.0.dist-info/RECORD
