Metadata-Version: 2.4
Name: spellcure
Version: 1.0.0
Summary: SpellCure — correction for highly scrambled text (Saheban Khan)
Author-email: Saheban Khan <sahebankhan21@gmail.com>
License-Expression: MIT
Requires-Python: >=3.8
Requires-Dist: nltk
Requires-Dist: textdistance
